LICENSE
README.md
crosshash.py
crosshash-0.3.4.dist-info/LICENSE
crosshash-0.3.4.dist-info/METADATA
crosshash-0.3.4.dist-info/WHEEL
crosshash-0.3.4.dist-info/entry_points.txt
crosshash-0.3.4.dist-info/RECORD
