Metadata-Version: 2.1
Name: crosshash
Version: 0.3.4
Summary: Stable, cross-platform JSON serialization and hashing for Python and JavaScript.
Home-page: https://github.com/httpie/crosshash
License: MIT
Author: Jakub Roztocil
Author-email: jakub@httpie.io
Requires-Python: >=3.11,<4.0
Classifier: License :: OSI Approved :: MIT License
Classifier: Programming Language :: Python :: 3
Classifier: Programming Language :: Python :: 3.11
Project-URL: Repository, https://github.com/httpie/crosshash
